enginepy/__init__.py
enginepy/tools.py
enginepy-1.0.4.dist-info/top_level.txt
enginepy-1.0.4.dist-info/METADATA
enginepy-1.0.4.dist-info/DESCRIPTION.rst
enginepy-1.0.4.dist-info/metadata.json
enginepy-1.0.4.dist-info/WHEEL
enginepy-1.0.4.dist-info/RECORD
