Metadata-Version: 2.0
Name: enginepy
Version: 1.0.4
Summary: A simple and powerful python API for running external commands.
Home-page: https://github.com/phenicle/enginepy
Author: Phenicle
Author-email: pheniclebeefheart@gmail.com
License: Mozilla Public License 2.0 (MPL 2.0)
Platform: UNKNOWN
